LICENSE
MANIFEST.in
README.md
setup.py
docs/main_menu.jpg
personal_assistant/Clean_folder.py
personal_assistant/Main_menu.py
personal_assistant/NoteBook.txt
personal_assistant/Notes.py
personal_assistant/Python_core_Team_3.py
personal_assistant/__init__.py
personal_assistant_cli_bot.egg-info/PKG-INFO
personal_assistant_cli_bot.egg-info/SOURCES.txt
personal_assistant_cli_bot.egg-info/dependency_links.txt
personal_assistant_cli_bot.egg-info/entry_points.txt
personal_assistant_cli_bot.egg-info/requires.txt
personal_assistant_cli_bot.egg-info/top_level.txt
pr_venv/Lib/site-packages/six.py
pr_venv/Lib/site-packages/textwrap3.py
pr_venv/Lib/site-packages/_distutils_hack/__init__.py
pr_venv/Lib/site-packages/_distutils_hack/override.py
pr_venv/Lib/site-packages/ansiwrap/__init__.py
pr_venv/Lib/site-packages/ansiwrap/ansistate.py
pr_venv/Lib/site-packages/ansiwrap/core.py
pr_venv/Lib/site-packages/bleach/__init__.py
pr_venv/Lib/site-packages/bleach/callbacks.py
pr_venv/Lib/site-packages/bleach/css_sanitizer.py
pr_venv/Lib/site-packages/bleach/html5lib_shim.py
pr_venv/Lib/site-packages/bleach/linkifier.py
pr_venv/Lib/site-packages/bleach/parse_shim.py
pr_venv/Lib/site-packages/bleach/sanitizer.py
pr_venv/Lib/site-packages/bleach/_vendor/__init__.py
pr_venv/Lib/site-packages/bleach/_vendor/parse.py
pr_venv/Lib/site-packages/bleach/_vendor/html5lib/__init__.py
pr_venv/Lib/site-packages/bleach/_vendor/html5lib/_ihatexml.py
pr_venv/Lib/site-packages/bleach/_vendor/html5lib/_inputstream.py
pr_venv/Lib/site-packages/bleach/_vendor/html5lib/_tokenizer.py
pr_venv/Lib/site-packages/bleach/_vendor/html5lib/_utils.py
pr_venv/Lib/site-packages/bleach/_vendor/html5lib/constants.py
pr_venv/Lib/site-packages/bleach/_vendor/html5lib/html5parser.py
pr_venv/Lib/site-packages/bleach/_vendor/html5lib/serializer.py
pr_venv/Lib/site-packages/bleach/_vendor/html5lib/_trie/__init__.py
pr_venv/Lib/site-packages/bleach/_vendor/html5lib/_trie/_base.py
pr_venv/Lib/site-packages/bleach/_vendor/html5lib/_trie/py.py
pr_venv/Lib/site-packages/bleach/_vendor/html5lib/filters/__init__.py
pr_venv/Lib/site-packages/bleach/_vendor/html5lib/filters/alphabeticalattributes.py
pr_venv/Lib/site-packages/bleach/_vendor/html5lib/filters/base.py
