Metadata-Version: 2.1
Name: personal-assistant-cli-bot
Version: 1.0.3
Summary: A personal assistant with a command line interface
Home-page: https://github.com/tetianakondra/Python_core_Team_3/blob/main/Python_core_Team_3.py
Author: Tetiana Kondra, Natalia Sokil, Yevhen Kosarev, Oleksandr Chepkanich, Andrii Holubenko
Author-email: t_prischepa@ukr.net, sokilnatalka@gmail.com, kossik89@gmail.com, a.chepkanich@gmail.com, andrii.holub82@gmail.com
License: MIT
Classifier: Programming Language :: Python :: 3
Classifier: License :: OSI Approved :: MIT License
Classifier: Operating System :: OS Independent
License-File: LICENSE
